CHANGES.txt
LICENSE.txt
MANIFEST
MANIFEST.in
setup.py
Docs/epydoc.css
Docs/index.html
Docs/private/ZestyParser-module.html
Docs/private/ZestyParser.AHT-module.html
Docs/private/ZestyParser.AHT.Env-class.html
Docs/private/ZestyParser.AHT._AHTFactory-class.html
Docs/private/ZestyParser.DebuggingParser-module.html
Docs/private/ZestyParser.DebuggingParser.DebuggingParser-class.html
Docs/private/ZestyParser.Helpers-module.html
Docs/private/ZestyParser.Helpers.EncloseHelper-class.html
Docs/private/ZestyParser.Helpers.EscapeHelper-class.html
Docs/private/ZestyParser.Helpers.IndentHelper-class.html
Docs/private/ZestyParser.Helpers.IndentationLevel-class.html
Docs/private/ZestyParser.Helpers.Oper-class.html
Docs/private/ZestyParser.Parser-module.html
Docs/private/ZestyParser.Parser.Error-class.html
Docs/private/ZestyParser.Parser.NotMatched-class.html
Docs/private/ZestyParser.Parser.ParseError-class.html
Docs/private/ZestyParser.Parser.ZestyParser-class.html
Docs/private/ZestyParser.Tags-module.html
Docs/private/ZestyParser.Tags._Env-class.html
Docs/private/ZestyParser.Tags._Tag-class.html
Docs/private/ZestyParser.Tokens-module.html
Docs/private/ZestyParser.Tokens.AbstractToken-class.html
Docs/private/ZestyParser.Tokens.CompositeToken-class.html
Docs/private/ZestyParser.Tokens.Default-class.html
Docs/private/ZestyParser.Tokens.Defer-class.html
Docs/private/ZestyParser.Tokens.ListReplacing-class.html
Docs/private/ZestyParser.Tokens.Lookahead-class.html
Docs/private/ZestyParser.Tokens.Negative-class.html
Docs/private/ZestyParser.Tokens.Omit-class.html
Docs/private/ZestyParser.Tokens.Only-class.html
Docs/private/ZestyParser.Tokens.Placeholder-class.html
Docs/private/ZestyParser.Tokens.RE-class.html
Docs/private/ZestyParser.Tokens.Raw-class.html
Docs/private/ZestyParser.Tokens.SingleReplacing-class.html
Docs/private/ZestyParser.Tokens.Skip-class.html
Docs/private/ZestyParser.Tokens.TakeToken-class.html
Docs/private/ZestyParser.Tokens.TokenSequence-class.html
ZestyParser.egg-info/PKG-INFO
ZestyParser.egg-info/SOURCES.txt
ZestyParser.egg-info/dependency_links.txt
ZestyParser.egg-info/top_level.txt
