Metadata-Version: 1.0
Name: ZestyParser
Version: 0.8.1
Summary: Write less parsing code. Write nicer parsing code. Have fun with it.
Home-page: http://adamatlas.org/2006/12/ZestyParser/
Author: Adam Atlas
Author-email: adam@atlas.st
License: MIT
Platform: UNKNOWN
Classifier: Development Status :: 4 - Beta
Classifier: Intended Audience :: Developers
Classifier: License :: OSI Approved :: MIT License
Classifier: Natural Language :: English
Classifier: Programming Language :: Python
Classifier: Topic :: Software Development :: Libraries :: Python Modules
Classifier: Topic :: Text Processing
